geeksales/__init__.py
geeksales/spark_utils.py
geeksales-0.1.1.dist-info/licenses/LICENSE
geeksales-0.1.1.dist-info/METADATA
geeksales-0.1.1.dist-info/WHEEL
geeksales-0.1.1.dist-info/top_level.txt
geeksales-0.1.1.dist-info/RECORD
